uszipcode/__init__.py
uszipcode/_version.py
uszipcode/db.py
uszipcode/model.py
uszipcode/search.py
uszipcode/state_abbr.py
uszipcode/__pycache__/__init__.cpython-38.pyc
uszipcode/__pycache__/_version.cpython-38.pyc
uszipcode/__pycache__/db.cpython-38.pyc
uszipcode/__pycache__/model.cpython-38.pyc
uszipcode/__pycache__/search.cpython-38.pyc
uszipcode/__pycache__/state_abbr.cpython-38.pyc
uszipcode/docs/__init__.py
uszipcode/docs/__pycache__/__init__.cpython-38.pyc
uszipcode/tests/__init__.py
uszipcode/tests/__pycache__/__init__.cpython-38.pyc
uszipcode-1.0.1.dist-info/AUTHORS.rst
uszipcode-1.0.1.dist-info/LICENSE.txt
uszipcode-1.0.1.dist-info/METADATA
uszipcode-1.0.1.dist-info/WHEEL
uszipcode-1.0.1.dist-info/top_level.txt
uszipcode-1.0.1.dist-info/RECORD
